app/__init__.py
app/diff_processor.py
app/git_commands.py
app/main.py
app/models.py
app/rtf_writer.py
clearcase2git-0.1.0.dist-info/METADATA
clearcase2git-0.1.0.dist-info/WHEEL
clearcase2git-0.1.0.dist-info/entry_points.txt
clearcase2git-0.1.0.dist-info/top_level.txt
clearcase2git-0.1.0.dist-info/RECORD
