Metadata-Version: 2.1
Name: clearcase2git
Version: 0.1.0
Summary: Migration of Perl scripts using Clearcase to Python scripts using Git
Requires-Python: >=3.7
